{
    "id": 1037,
    "rated": 0,
    "tim": "2022/03/29 18:53:17",
    "stat": "FINISHED",
    "user1": "Qkkky",
    "user2": "taxiing",
    "user1_score": "-",
    "user2_score": "WA",
    "output": "#.#..####\n####.##.#\n.#.###.##\n.#####.##\n.##.##..#\n.#####.##\n.#.###.##\n####.##.#\n#.#..####\n0 2 0 4\n1 0 3\n2 0 1\n3 0 2\n4 0 0\n5 0 2\n6 0 0\n7 0 1\n8 0 0\n9 0 1\n10 0 0\n11 0 0\n12 0 0\n13 0 1\n14 0 3\n15 0 0\n16 0 2\n17 0 1\n18 0 2\n19 0 1\n20 1 0 7\n21 0 3\n22 0 3\n23 0 3\n24 0 3\n25 0 3\n26 0 0\n27 0 2\n28 0 0\n29 0 1\n30 0 3\n31 0 2\n32 0 2\n33 0 1\n34 0 2\n35 0 2\n36 0 2\n37 0 1\n38 0 2\n39 0 2\n40 0 1\n41 0 2\n42 0 1\n43 0 2\n44 0 0\n45 0 2\n46 0 1\n47 0 2\n48 2 7 7\n49 0 0\n50 1 3 7\n51 0 0\n52 2 5 7\n53 0 0\n54 1 4 6\n55 0 0\n56 2 3 5\n57 0 3\n58 1 2 6\n59 0 1\n60 2 2 4\n61 0 2\n62 2 1 5\n63 0 2\n64 0 1\n65 0 2\n66 0 1\n67 0 2\n68 0 2\n- WA\nEND\n"
}